ricercasociale/__init__.py
ricercasociale/crosstab.py
ricercasociale/monovariata.py
ricercasociale-0.2.dist-info/DESCRIPTION.rst
ricercasociale-0.2.dist-info/METADATA
ricercasociale-0.2.dist-info/RECORD
ricercasociale-0.2.dist-info/WHEEL
ricercasociale-0.2.dist-info/metadata.json
ricercasociale-0.2.dist-info/top_level.txt
