Metadata-Version: 2.0
Name: ricercasociale
Version: 0.2
Summary: grafici e tabelle per le scienze sociali
Home-page: https://github.com/scarsellifi/ricercasociale.git
Author: Marco Scarselli
Author-email: scarselli@gmail.com
License: MIT
Platform: UNKNOWN
Requires-Dist: matplotlib
Requires-Dist: numpy
Requires-Dist: pandas
Requires-Dist: seaborn
